tinyhtml/__init__.py
tinyhtml/py.typed
tinyhtml-1.3.0.dist-info/LICENSE-APACHE
tinyhtml-1.3.0.dist-info/LICENSE-MIT
tinyhtml-1.3.0.dist-info/METADATA
tinyhtml-1.3.0.dist-info/WHEEL
tinyhtml-1.3.0.dist-info/top_level.txt
tinyhtml-1.3.0.dist-info/RECORD
