Metadata-Version: 2.2
Name: tinyhtml
Version: 1.3.0
Summary: A tiny library to safely render compact HTML5 from Python expressions.
Home-page: https://github.com/niklasf/python-tinyhtml
Author: Niklas Fiekas
Author-email: niklas.fiekas@backscattering.de
License: MIT/Apache-2.0
Keywords: html html5 vdom functional-programming
Classifier: Development Status :: 5 - Production/Stable
Classifier: Intended Audience :: Developers
Classifier: License :: OSI Approved :: MIT License
Classifier: License :: OSI Approved :: Apache Software License
Classifier: Operating System :: OS Independent
Classifier: Programming Language :: Python :: 3 :: Only
Classifier: Programming Language :: Python :: 3.8
Classifier: Programming Language :: Python :: 3.9
Classifier: Programming Language :: Python :: 3.10
Classifier: Programming Language :: Python :: 3.11
Classifier: Programming Language :: Python :: 3.12
Classifier: Programming Language :: Python :: 3.13
Classifier: Topic :: Internet :: WWW/HTTP
Classifier: Topic :: Software Development :: Libraries :: Python Modules
Classifier: Topic :: Text Processing :: Markup :: HTML
Classifier: Typing :: Typed
Requires-Python: >=3.8
License-File: LICENSE-APACHE
License-File: LICENSE-MIT
Provides-Extra: test
Requires-Dist: jinja2; extra == "test"
Requires-Dist: pandas; extra == "test"
Dynamic: author
Dynamic: author-email
Dynamic: classifier
Dynamic: description
Dynamic: description-content-type
Dynamic: home-page
Dynamic: keywords
Dynamic: license
Dynamic: provides-extra
Dynamic: requires-python
Dynamic: summary
